{
    "creatureStatistics":  {
                               "name":  "Pemaret",
                               "health":  100,
                               "maxHealth":  100,
                               "mana":  0,
                               "maxMana":  0,
                               "attack":  1,
                               "attackSlowness":  40,
                               "defense":  5,
                               "speed":  30,
                               "outfit":  {
                                              "id":  111,
                                              "details":  {
                                                              "head":  79,
                                                              "body":  10,
                                                              "legs":  127,
                                                              "feet":  127
                                                          }
                                          }
                           },
    "behaviour":  {
                      "wanderRange":  1,
                      "openDoors":  true,
                      "ignoreCharacters":  true
                  },
    "conversation":  {
                         "hearingRange":  5,
                         "keywords":  {
                                          "name":  "My name is Pemaret, the fisherman.",
                                          "job":  "I\u0027m a fisherman and I take along people to Edron. You can also buy some fresh fish.",
                                          "tibia":  "I love to sail on the seas of Tibia.",
                                          "sea":  "I love to sail on the seas of Tibia.",
                                          "cormaya":  "It\u0027s a lovely and peaceful isle. Did you already visit the nice sandy beach?",
                                          "isle":  "It\u0027s a lovely and peaceful isle. Did you already visit the nice sandy beach?",
                                          "beach":  "There is a nice sandy beach in the west of Cormaya.",
                                          "ship":  "My boat is ready to bring you to Edron.",
                                          "boat":  "My boat is ready to bring you to Edron.",
                                          "passage":  "My boat is ready to bring you to Edron.",
                                          "edron":  "Do you want to get to Edron for 10 gold?",
                                          "eremo":  "Oh, you know the good old sage Eremo. I can bring you to his little island. Do you want me to do that?",
                                          "sage":  "Oh, you know the good old sage Eremo. I can bring you to his little island. Do you want me to do that?"
                                      },
                         "farewells":  [
                                           "bye",
                                           "goodbye",
                                           "farewell"
                                       ],
                         "greetings":  [
                                           "hello",
                                           "hi",
                                           "greetings"
                                       ],
                         "sayings":  {
                                         "texts":  [
                                                       "Greetings, young man. Looking for a passage or some fish, ?",
                                                       "Greetings, young lady. Looking for a passage or some fish, ?",
                                                       "I\u0027m a fisherman and I take along people to Edron. You can also buy some fresh fish."
                                                   ],
                                         "rate":  300,
                                         "chance":  0.1
                                     },
                         "punishments":  {

                                         },
                         "greetingPatterns":  [
                                                  {
                                                      "keywords":  [
                                                                       "hello$"
                                                                   ],
                                                      "response":  "Greetings, young man. Looking for a passage or some fish, %N?",
                                                      "idle":  false
                                                  },
                                                  {
                                                      "keywords":  [
                                                                       "hi$"
                                                                   ],
                                                      "response":  null,
                                                      "idle":  false
                                                  },
                                                  {
                                                      "keywords":  [
                                                                       "hello$"
                                                                   ],
                                                      "response":  "Greetings, young lady. Looking for a passage or some fish, %N?",
                                                      "idle":  false
                                                  },
                                                  {
                                                      "keywords":  [
                                                                       "hi$"
                                                                   ],
                                                      "response":  null,
                                                      "idle":  false
                                                  }
                                              ],
                         "topics":  {
                                        "1":  {
                                                  "entries":  [
                                                                  {
                                                                      "keywords":  [
                                                                                       "yes"
                                                                                   ],
                                                                      "response":  "Here we go!",
                                                                      "conditions":  [
                                                                                         {
                                                                                             "type":  "gold",
                                                                                             "min":  -1
                                                                                         }
                                                                                     ],
                                                                      "actions":  [
                                                                                      {
                                                                                          "type":  "deleteMoney",
                                                                                          "amount":  -1
                                                                                      },
                                                                                      {
                                                                                          "type":  "teleport",
                                                                                          "x":  33182,
                                                                                          "y":  31764,
                                                                                          "z":  7
                                                                                      }
                                                                                  ],
                                                                      "nextTopic":  null,
                                                                      "idle":  true
                                                                  },
                                                                  {
                                                                      "keywords":  [
                                                                                       "yes"
                                                                                   ],
                                                                      "response":  "You don\u0027t have enough money.",
                                                                      "conditions":  [

                                                                                     ],
                                                                      "actions":  [

                                                                                  ],
                                                                      "nextTopic":  null,
                                                                      "idle":  false
                                                                  },
                                                                  {
                                                                      "keywords":  [

                                                                                   ],
                                                                      "response":  "Maybe later.",
                                                                      "conditions":  [

                                                                                     ],
                                                                      "actions":  [

                                                                                  ],
                                                                      "nextTopic":  null,
                                                                      "idle":  true,
                                                                      "isDefault":  true
                                                                  }
                                                              ]
                                              },
                                        "2":  {
                                                  "entries":  [
                                                                  {
                                                                      "keywords":  [
                                                                                       "yes"
                                                                                   ],
                                                                      "response":  "Here it is.",
                                                                      "conditions":  [
                                                                                         {
                                                                                             "type":  "gold",
                                                                                             "min":  -1
                                                                                         }
                                                                                     ],
                                                                      "actions":  [
                                                                                      {
                                                                                          "type":  "deleteMoney",
                                                                                          "amount":  -1
                                                                                      },
                                                                                      {
                                                                                          "type":  "createItem",
                                                                                          "id":  -1
                                                                                      }
                                                                                  ],
                                                                      "nextTopic":  null,
                                                                      "idle":  false
                                                                  },
                                                                  {
                                                                      "keywords":  [
                                                                                       "yes"
                                                                                   ],
                                                                      "response":  "I am sorry, but you do not have enough gold.",
                                                                      "conditions":  [

                                                                                     ],
                                                                      "actions":  [

                                                                                  ],
                                                                      "nextTopic":  null,
                                                                      "idle":  false
                                                                  },
                                                                  {
                                                                      "keywords":  [

                                                                                   ],
                                                                      "response":  "Maybe later.",
                                                                      "conditions":  [

                                                                                     ],
                                                                      "actions":  [

                                                                                  ],
                                                                      "nextTopic":  null,
                                                                      "idle":  true,
                                                                      "isDefault":  true
                                                                  }
                                                              ]
                                              },
                                        "3":  {
                                                  "entries":  [
                                                                  {
                                                                      "keywords":  [
                                                                                       "yes"
                                                                                   ],
                                                                      "response":  "Here we go!",
                                                                      "conditions":  [

                                                                                     ],
                                                                      "actions":  [
                                                                                      {
                                                                                          "type":  "teleport",
                                                                                          "x":  33315,
                                                                                          "y":  31882,
                                                                                          "z":  7
                                                                                      }
                                                                                  ],
                                                                      "nextTopic":  null,
                                                                      "idle":  true
                                                                  },
                                                                  {
                                                                      "keywords":  [

                                                                                   ],
                                                                      "response":  "Maybe later.",
                                                                      "conditions":  [

                                                                                     ],
                                                                      "actions":  [

                                                                                  ],
                                                                      "nextTopic":  null,
                                                                      "idle":  true,
                                                                      "isDefault":  true
                                                                  }
                                                              ]
                                              }
                                    },
                         "keywordNextTopics":  {
                                                   "edron":  1,
                                                   "eremo":  3,
                                                   "sage":  3
                                               },
                         "keywordTopicPrices":  {
                                                    "edron":  10
                                                },
                         "trade":  {
                                       "items":  [
                                                     {
                                                         "name":  "Fish",
                                                         "price":  5,
                                                         "id":  2667,
                                                         "type":  "sell"
                                                     }
                                                 ]
                                   },
                         "script":  "pemaret.js"
                     }
}
